emm/__init__.py
emm/config.py
emm/main.py
emm/chat/__init__.py
emm/chat/chat.py
emm/query/__init__.py
emm/query/query.py
emm/ui/__init__.py
emm/ui/answer.py
emm/ui/selector.py
emm/utils/__init__.py
emm/utils/config.py
emm/utils/sysinfo.py
emm_cmd-2.0.dist-info/LICENCE.md
emm_cmd-2.0.dist-info/METADATA
emm_cmd-2.0.dist-info/WHEEL
emm_cmd-2.0.dist-info/entry_points.txt
emm_cmd-2.0.dist-info/top_level.txt
emm_cmd-2.0.dist-info/RECORD
