Metadata-Version: 2.1
Name: emm-cmd
Version: 2.0
Summary: AI command line assistant.
Author: Chunyang
Requires-Python: >=3.6
License-File: LICENCE.md
Requires-Dist: appdirs ==1.4.4
Requires-Dist: inquirerpy ==0.3.4
Requires-Dist: openai ==1.3.5
Requires-Dist: psutil ==5.9.6
Requires-Dist: Pygments ==2.17.2
Requires-Dist: rich ==13.7.0
Requires-Dist: typer ==0.9.0
Requires-Dist: readme-renderer ==42.0
Requires-Dist: art ==6.1
